{
  "items": {
    "11566": [
      {
        "goods_type": 0,
        "goods_id": "539273",
        "goods_sn": "268952805",
        "is_on_sale": "1",
        "goods_number": "981",
        "promte_percent": "0.84",
        "activity_number": "0",
        "activity_volume_number": "0",
        "goods_title": "Spaghetti Strap Criss Cross Bikini",
        "url_quick": "http://www.pc-zaful.com.v0731_tr.php5.egomsl.com/m-goods_fast-a-info.htm?goods_id=539273&ge_newindex=1",
        "url_title": "http://www.pc-zaful.com.v0731_tr.php5.egomsl.com/spaghetti-strap-criss-cross-bikini-p_539273.html",
        "goods_img": "https://gloimg.zafcdn.com/zaful/pdm-product-pic/Clothing/2018/06/07/goods-img/1529870341069017764.jpg",
        "market_price": "10.00",
        "shop_price": "11.97",
        "discount": -20,
        "warehousecode": "ZQ01",
        "cateid": "67",
        "catename": "Bikinis",
        "promotions": [],
        "promote_start_date": "2019-05-05",
        "promote_end_date": "2020-07-01",
        "promote_start_time": "1556985600",
        "promote_end_time": "1593532800",
        "score_rank": 0,
        "review_total": 0,
        "left_time": 29146184,
        "is_show": 1,
        "catid": "67",
        "category": "Bikinis",
        "warecode": "ZQ01"
      },
      {
        "goods_type": 0,
        "goods_id": "539296",
        "goods_sn": "268952804",
        "is_on_sale": "1",
        "goods_number": "1004",
        "promte_percent": "0.84",
        "activity_number": "0",
        "activity_volume_number": "0",
        "goods_title": "Spaghetti Strap Criss Cross Bikini",
        "url_quick": "http://www.pc-zaful.com.v0731_tr.php5.egomsl.com/m-goods_fast-a-info.htm?goods_id=539296&ge_newindex=1",
        "url_title": "http://www.pc-zaful.com.v0731_tr.php5.egomsl.com/spaghetti-strap-criss-cross-bikini-p_539296.html",
        "goods_img": "https://gloimg.zafcdn.com/zaful/pdm-product-pic/Clothing/2018/06/07/goods-img/1529870402284785478.jpg",
        "market_price": "10.00",
        "shop_price": "11.97",
        "discount": -20,
        "warehousecode": "ZQ01",
        "cateid": "67",
        "catename": "Bikinis",
        "promotions": [],
        "promote_start_date": "2019-05-05",
        "promote_end_date": "2020-07-01",
        "promote_start_time": "1556985600",
        "promote_end_time": "1593532800",
        "score_rank": 0,
        "review_total": 0,
        "left_time": 29146184,
        "is_show": 1,
        "catid": "67",
        "category": "Bikinis",
        "warecode": "ZQ01"
      },
      {
        "goods_type": 0,
        "goods_id": "566074",
        "goods_sn": "280716601",
        "is_on_sale": "1",
        "goods_number": "1080",
        "promte_percent": "1.62",
        "activity_number": "0",
        "activity_volume_number": "0",
        "goods_title": "ZAFUL Flower Twist High Waisted Bikini Set",
        "url_quick": "http://www.pc-zaful.com.v0731_tr.php5.egomsl.com/m-goods_fast-a-info.htm?goods_id=566074&ge_newindex=1",
        "url_title": "http://www.pc-zaful.com.v0731_tr.php5.egomsl.com/zaful-flower-twist-high-waisted-bikini-set-p_566074.html",
        "goods_img": "https://gloimg.zafcdn.com/zaful/pdm-product-pic/Clothing/2018/08/30/goods-img/1535990763437434019.jpg",
        "market_price": "15.99",
        "shop_price": "9.90",
        "discount": 0,
        "warehousecode": "ZQ01",
        "cateid": "67",
        "catename": "Bikinis",
        "promotions": [],
        "promote_start_date": "",
        "promote_end_date": "",
        "promote_start_time": 0,
        "promote_end_time": 0,
        "score_rank": 0,
        "review_total": 0,
        "left_time": 0,
        "is_show": 1,
        "catid": "67",
        "category": "Bikinis",
        "warecode": "ZQ01"
      },
      {
        "goods_type": 0,
        "goods_id": "566049",
        "goods_sn": "280716602",
        "is_on_sale": "1",
        "goods_number": "1080",
        "promte_percent": "0.94",
        "activity_number": "0",
        "activity_volume_number": "0",
        "goods_title": "ZAFUL Flower Twist High Waisted Bikini Set",
        "url_quick": "http://www.pc-zaful.com.v0731_tr.php5.egomsl.com/m-goods_fast-a-info.htm?goods_id=566049&ge_newindex=1",
        "url_title": "http://www.pc-zaful.com.v0731_tr.php5.egomsl.com/zaful-flower-twist-high-waisted-bikini-set-p_566049.html",
        "goods_img": "https://gloimg.zafcdn.com/zaful/pdm-product-pic/Clothing/2018/08/30/goods-img/1535990331144678424.jpg",
        "market_price": "15.99",
        "shop_price": "16.99",
        "discount": 0,
        "warehousecode": "ZQ01",
        "cateid": "67",
        "catename": "Bikinis",
        "promotions": [],
        "promote_start_date": "",
        "promote_end_date": "",
        "promote_start_time": 0,
        "promote_end_time": 0,
        "score_rank": 0,
        "review_total": 0,
        "left_time": 0,
        "is_show": 1,
        "catid": "67",
        "category": "Bikinis",
        "warecode": "ZQ01"
      },
      {
        "goods_type": 0,
        "goods_id": "566060",
        "goods_sn": "280716603",
        "is_on_sale": "1",
        "goods_number": "37",
        "promte_percent": "0.94",
        "activity_number": "0",
        "activity_volume_number": "0",
        "goods_title": "ZAFUL Flower Twist High Waisted Bikini Set",
        "url_quick": "http://www.pc-zaful.com.v0731_tr.php5.egomsl.com/m-goods_fast-a-info.htm?goods_id=566060&ge_newindex=1",
        "url_title": "http://www.pc-zaful.com.v0731_tr.php5.egomsl.com/zaful-flower-twist-high-waisted-bikini-set-p_566060.html",
        "goods_img": "https://gloimg.zafcdn.com/zaful/pdm-product-pic/Clothing/2018/08/30/goods-img/1535990375812822275.jpg",
        "market_price": "15.99",
        "shop_price": "16.99",
        "discount": 0,
        "warehousecode": "ZQ01",
        "cateid": "67",
        "catename": "Bikinis",
        "promotions": [],
        "promote_start_date": "",
        "promote_end_date": "",
        "promote_start_time": 0,
        "promote_end_time": 0,
        "score_rank": 0,
        "review_total": 0,
        "left_time": 0,
        "is_show": 1,
        "catid": "67",
        "category": "Bikinis",
        "warecode": "ZQ01"
      },
      {
        "goods_type": 0,
        "goods_id": "410581",
        "goods_sn": "232364203",
        "is_on_sale": "1",
        "goods_number": "82",
        "promte_percent": "1.13",
        "activity_number": "0",
        "activity_volume_number": "0",
        "goods_title": "Hooded Color Block Corduroy Jacket",
        "url_quick": "http://www.pc-zaful.com.v0731_tr.php5.egomsl.com/m-goods_fast-a-info.htm?goods_id=410581&ge_newindex=1",
        "url_title": "http://www.pc-zaful.com.v0731_tr.php5.egomsl.com/hooded-color-block-corduroy-jacket-p_410581.html",
        "goods_img": "https://gloimg.zafcdn.com/zaful/pdm-product-pic/Clothing/2017/12/08/goods-img/1512695836459019017.jpg",
        "market_price": "57.83",
        "shop_price": "50.99",
        "discount": 0,
        "warehousecode": "ZQ01",
        "cateid": "8",
        "catename": "Jackets & Coats",
        "promotions": [],
        "promote_start_date": "",
        "promote_end_date": "",
        "promote_start_time": 0,
        "promote_end_time": 0,
        "score_rank": 0,
        "review_total": 0,
        "left_time": 0,
        "is_show": 1,
        "catid": "8",
        "category": "Jackets & Coats",
        "warecode": "ZQ01"
      },
      {
        "goods_type": 0,
        "goods_id": "554107",
        "goods_sn": "276459304",
        "is_on_sale": "1",
        "goods_number": "929",
        "promte_percent": "1.62",
        "activity_number": "0",
        "activity_volume_number": "0",
        "goods_title": "Chest Letter Print Solid Color Suede Sweatshirt",
        "url_quick": "http://www.pc-zaful.com.v0731_tr.php5.egomsl.com/m-goods_fast-a-info.htm?goods_id=554107&ge_newindex=1",
        "url_title": "http://www.pc-zaful.com.v0731_tr.php5.egomsl.com/chest-letter-print-solid-color-suede-sweatshirt-p_554107.html",
        "goods_img": "https://gloimg.zafcdn.com/zaful/pdm-product-pic/Clothing/2018/08/20/goods-img/1534723229607193480.jpg",
        "market_price": "45.25",
        "shop_price": "27.99",
        "discount": 0,
        "warehousecode": "ZQ01",
        "cateid": "139",
        "catename": "Hoodies & Sweatshirts",
        "promotions": [],
        "promote_start_date": "",
        "promote_end_date": "",
        "promote_start_time": 0,
        "promote_end_time": 0,
        "score_rank": 0,
        "review_total": 0,
        "left_time": 0,
        "is_show": 1,
        "catid": "139",
        "category": "Hoodies & Sweatshirts",
        "warecode": "ZQ01"
      },
      {
        "goods_type": 0,
        "goods_id": "539257",
        "goods_sn": "268952802",
        "is_on_sale": "1",
        "goods_number": "0",
        "promte_percent": "0.84",
        "activity_number": "0",
        "activity_volume_number": "0",
        "goods_title": "Spaghetti Strap Criss Cross Bikini",
        "url_quick": "http://www.pc-zaful.com.v0731_tr.php5.egomsl.com/m-goods_fast-a-info.htm?goods_id=539257&ge_newindex=1",
        "url_title": "http://www.pc-zaful.com.v0731_tr.php5.egomsl.com/spaghetti-strap-criss-cross-bikini-p_539257.html",
        "goods_img": "https://gloimg.zafcdn.com/zaful/pdm-product-pic/Clothing/2018/06/07/goods-img/1533081148286074904.jpg",
        "market_price": "10.00",
        "shop_price": "11.97",
        "discount": -20,
        "warehousecode": "ZQ01",
        "cateid": "67",
        "catename": "Bikinis",
        "promotions": [],
        "promote_start_date": "2019-05-05",
        "promote_end_date": "2020-07-01",
        "promote_start_time": "1556985600",
        "promote_end_time": "1593532800",
        "score_rank": 0,
        "review_total": 0,
        "left_time": 29146184,
        "is_show": 1,
        "catid": "67",
        "category": "Bikinis",
        "warecode": "ZQ01"
      },
      {
        "goods_type": 0,
        "goods_id": "566082",
        "goods_sn": "276426201",
        "is_on_sale": "1",
        "goods_number": "0",
        "promte_percent": "1.56",
        "activity_number": "0",
        "activity_volume_number": "0",
        "goods_title": "ZAFUL Two Tone Hoodie and Sports Pants Set",
        "url_quick": "http://www.pc-zaful.com.v0731_tr.php5.egomsl.com/m-goods_fast-a-info.htm?goods_id=566082&ge_newindex=1",
        "url_title": "http://www.pc-zaful.com.v0731_tr.php5.egomsl.com/zaful-two-tone-hoodie-and-sports-pants-set-p_566082.html",
        "goods_img": "https://gloimg.zafcdn.com/zaful/pdm-product-pic/Clothing/2018/08/30/goods-img/1535995023471077733.jpg",
        "market_price": "81.25",
        "shop_price": "51.99",
        "discount": 0,
        "warehousecode": "ZQ01",
        "cateid": "175",
        "catename": "Polo Shirts",
        "promotions": [],
        "promote_start_date": "",
        "promote_end_date": "",
        "promote_start_time": 0,
        "promote_end_time": 0,
        "score_rank": 0,
        "review_total": 0,
        "left_time": 0,
        "is_show": 1,
        "catid": "175",
        "category": "Polo Shirts",
        "warecode": "ZQ01"
      }
    ],
    "12564": [
      {
        "goods_type": 1, "goods_id": "278541", "goods_sn": "212363402", "is_on_sale": "1", "goods_number": "957",
        "promte_percent": "0.97", "activity_number": "0", "activity_volume_number": "0",
        "goods_title": "Off Shoulder Shirred Slit Floral Maxi Dress",
        "url_quick": "http://www.pc-zaful.com.v0731_tr.php5.egomsl.com/m-goods_fast-a-info.htm?goods_id=278541&ge_newindex=1",
        "url_title": "http://www.pc-zaful.com.v0731_tr.php5.egomsl.com/off-shoulder-shirred-slit-floral-maxi-dress-p_278541.html",
        "goods_img": "https://gloimg.zafcdn.com/zaful/pdm-product-pic/Clothing/2017/05/06/goods-img/1496715782753786870.jpg",
        "market_price": "49.24", "shop_price": "50.99", "discount": 0, "warehousecode": "ZQ01", "cateid": "41",
        "catename": "Maxi Dresses", "promotions": [
        "Buy 1 Get 1 <em class=\"special fb\">1% Off</em>", "Buy 2 Get 1 <em class=\"special fb\">2% Off</em>"
      ], "promote_start_date": "", "promote_end_date": "", "promote_start_time": 0, "promote_end_time": 0,
        "score_rank": 0, "review_total": 0, "left_time": 0, "is_show": 1, "catid": "41", "category": "Maxi Dresses",
        "warecode": "ZQ01", "show_market_price": false
      }, {
        "goods_type": 0, "goods_id": "305706", "goods_sn": "222799103", "is_on_sale": "1", "goods_number": "994",
        "promte_percent": "0.94", "activity_number": "0", "activity_volume_number": "0",
        "goods_title": "Floral Asymmetrical Wrap Maxi Dress",
        "url_quick": "http://www.pc-zaful.com.v0731_tr.php5.egomsl.com/m-goods_fast-a-info.htm?goods_id=305706&ge_newindex=1",
        "url_title": "http://www.pc-zaful.com.v0731_tr.php5.egomsl.com/floral-asymmetrical-wrap-maxi-dress-p_305706.html",
        "goods_img": "https://gloimg.zafcdn.com/zaful/pdm-product-pic/Clothing/2017/08/10/goods-img/1510287880435446228.jpg",
        "market_price": "31.92", "shop_price": "33.99", "discount": 0, "warehousecode": "ZQ01", "cateid": "41",
        "catename": "Maxi Dresses", "promotions": [], "promote_start_date": "", "promote_end_date": "",
        "promote_start_time": 0, "promote_end_time": 0, "score_rank": 0, "review_total": 0, "left_time": 0, "is_show": 1,
        "catid": "41", "category": "Maxi Dresses", "warecode": "ZQ01", "show_market_price": false
      }, {
        "goods_type": 0, "goods_id": "517638", "goods_sn": "255989505", "is_on_sale": "1", "goods_number": "996",
        "promte_percent": "0.95", "activity_number": "0", "activity_volume_number": "0",
        "goods_title": "Cami Floral Criss Cross Maxi Dress",
        "url_quick": "http://www.pc-zaful.com.v0731_tr.php5.egomsl.com/m-goods_fast-a-info.htm?goods_id=517638&ge_newindex=1",
        "url_title": "http://www.pc-zaful.com.v0731_tr.php5.egomsl.com/cami-floral-criss-cross-maxi-dress-p_517638.html",
        "goods_img": "https://gloimg.zafcdn.com/zaful/pdm-product-pic/Clothing/2018/01/25/goods-img/1517851445049701730.jpg",
        "market_price": "38.82", "shop_price": "40.99", "discount": 0, "warehousecode": "ZQ01", "cateid": "41",
        "catename": "Maxi Dresses", "promotions": [], "promote_start_date": "", "promote_end_date": "",
        "promote_start_time": 0, "promote_end_time": 0, "score_rank": 0, "review_total": 0, "left_time": 0, "is_show": 1,
        "catid": "41", "category": "Maxi Dresses", "warecode": "ZQ01", "show_market_price": false
      }, {
        "goods_type": 0, "goods_id": "566064", "goods_sn": "278697405", "is_on_sale": "1", "goods_number": "18",
        "promte_percent": "35.12", "activity_number": "0", "activity_volume_number": "0",
        "goods_title": "ZAFUL Ethnic Print Button Up Shirt",
        "url_quick": "http://www.pc-zaful.com.v0731_tr.php5.egomsl.com/m-goods_fast-a-info.htm?goods_id=566064&ge_newindex=1",
        "url_title": "http://www.pc-zaful.com.v0731_tr.php5.egomsl.com/zaful-ethnic-print-button-up-shirt-p_566064.html",
        "goods_img": "https://gloimg.zafcdn.com/zaful/pdm-product-pic/Clothing/2018/08/20/goods-img/1535990390690819564.jpg",
        "market_price": "34.77", "shop_price": "0.99", "discount": 0, "warehousecode": "ZQ01", "cateid": "138",
        "catename": "Shirts", "promotions": [], "promote_start_date": "", "promote_end_date": "", "promote_start_time": 0,
        "promote_end_time": 0, "score_rank": 0, "review_total": 0, "left_time": 0, "is_show": 1, "catid": "138",
        "category": "Shirts", "warecode": "ZQ01", "show_market_price": true
      }, {
        "goods_type": 0, "goods_id": "566067", "goods_sn": "279151305", "is_on_sale": "1", "goods_number": "38",
        "promte_percent": "0.91", "activity_number": "0", "activity_volume_number": "0",
        "goods_title": "ZAFUL Ruffles Trim Off Shoulder Crop Sweater",
        "url_quick": "http://www.pc-zaful.com.v0731_tr.php5.egomsl.com/m-goods_fast-a-info.htm?goods_id=566067&ge_newindex=1",
        "url_title": "http://www.pc-zaful.com.v0731_tr.php5.egomsl.com/zaful-ruffles-trim-off-shoulder-crop-sweater-p_566067.html",
        "goods_img": "https://gloimg.zafcdn.com/zaful/pdm-product-pic/Clothing/2018/08/27/goods-img/1535990403218341567.jpg",
        "market_price": "21.93", "shop_price": "23.99", "discount": 0, "warehousecode": "ZQ01", "cateid": "7",
        "catename": "Sweaters", "promotions": [], "promote_start_date": "", "promote_end_date": "",
        "promote_start_time": 0, "promote_end_time": 0, "score_rank": 0, "review_total": 0, "left_time": 0, "is_show": 1,
        "catid": "7", "category": "Sweaters", "warecode": "ZQ01", "show_market_price": false
      }
    ],
    "11625": [
      {
        "goods_type": 0, "goods_id": "539273", "goods_sn": "268952805", "is_on_sale": "1", "goods_number": "981",
        "promte_percent": "0.84", "activity_number": "0", "activity_volume_number": "0",
        "goods_title": "Spaghetti Strap Criss Cross Bikini",
        "url_quick": "http://www.pc-zaful.com.v0731_tr.php5.egomsl.com/m-goods_fast-a-info.htm?goods_id=539273&ge_newindex=1",
        "url_title": "http://www.pc-zaful.com.v0731_tr.php5.egomsl.com/spaghetti-strap-criss-cross-bikini-p_539273.html",
        "goods_img": "https://gloimg.zafcdn.com/zaful/pdm-product-pic/Clothing/2018/06/07/goods-img/1529870341069017764.jpg",
        "market_price": "10.00", "shop_price": "11.97", "discount": -20, "warehousecode": "ZQ01", "cateid": "67",
        "catename": "Bikinis", "promotions": [], "promote_start_date": "2019-05-05", "promote_end_date": "2020-07-01",
        "promote_start_time": "1556985600", "promote_end_time": "1593532800", "score_rank": 0, "review_total": 0,
        "left_time": 29146184, "is_show": 1, "catid": "67", "category": "Bikinis", "warecode": "ZQ01"
      }, {
        "goods_type": 0, "goods_id": "539296", "goods_sn": "268952804", "is_on_sale": "1", "goods_number": "1004",
        "promte_percent": "0.84", "activity_number": "0", "activity_volume_number": "0",
        "goods_title": "Spaghetti Strap Criss Cross Bikini",
        "url_quick": "http://www.pc-zaful.com.v0731_tr.php5.egomsl.com/m-goods_fast-a-info.htm?goods_id=539296&ge_newindex=1",
        "url_title": "http://www.pc-zaful.com.v0731_tr.php5.egomsl.com/spaghetti-strap-criss-cross-bikini-p_539296.html",
        "goods_img": "https://gloimg.zafcdn.com/zaful/pdm-product-pic/Clothing/2018/06/07/goods-img/1529870402284785478.jpg",
        "market_price": "10.00", "shop_price": "11.97", "discount": -20, "warehousecode": "ZQ01", "cateid": "67",
        "catename": "Bikinis", "promotions": [], "promote_start_date": "2019-05-05", "promote_end_date": "2020-07-01",
        "promote_start_time": "1556985600", "promote_end_time": "1593532800", "score_rank": 0, "review_total": 0,
        "left_time": 29146184, "is_show": 1, "catid": "67", "category": "Bikinis", "warecode": "ZQ01"
      }, {
        "goods_type": 0, "goods_id": "566074", "goods_sn": "280716601", "is_on_sale": "1", "goods_number": "1080",
        "promte_percent": "1.62", "activity_number": "0", "activity_volume_number": "0",
        "goods_title": "ZAFUL Flower Twist High Waisted Bikini Set",
        "url_quick": "http://www.pc-zaful.com.v0731_tr.php5.egomsl.com/m-goods_fast-a-info.htm?goods_id=566074&ge_newindex=1",
        "url_title": "http://www.pc-zaful.com.v0731_tr.php5.egomsl.com/zaful-flower-twist-high-waisted-bikini-set-p_566074.html",
        "goods_img": "https://gloimg.zafcdn.com/zaful/pdm-product-pic/Clothing/2018/08/30/goods-img/1535990763437434019.jpg",
        "market_price": "15.99", "shop_price": "9.90", "discount": 0, "warehousecode": "ZQ01", "cateid": "67",
        "catename": "Bikinis", "promotions": [], "promote_start_date": "", "promote_end_date": "",
        "promote_start_time": 0, "promote_end_time": 0, "score_rank": 0, "review_total": 0, "left_time": 0,
        "is_show": 1, "catid": "67", "category": "Bikinis", "warecode": "ZQ01"
      }, {
        "goods_type": 0, "goods_id": "566049", "goods_sn": "280716602", "is_on_sale": "1", "goods_number": "1080",
        "promte_percent": "0.94", "activity_number": "0", "activity_volume_number": "0",
        "goods_title": "ZAFUL Flower Twist High Waisted Bikini Set",
        "url_quick": "http://www.pc-zaful.com.v0731_tr.php5.egomsl.com/m-goods_fast-a-info.htm?goods_id=566049&ge_newindex=1",
        "url_title": "http://www.pc-zaful.com.v0731_tr.php5.egomsl.com/zaful-flower-twist-high-waisted-bikini-set-p_566049.html",
        "goods_img": "https://gloimg.zafcdn.com/zaful/pdm-product-pic/Clothing/2018/08/30/goods-img/1535990331144678424.jpg",
        "market_price": "15.99", "shop_price": "16.99", "discount": 0, "warehousecode": "ZQ01", "cateid": "67",
        "catename": "Bikinis", "promotions": [], "promote_start_date": "", "promote_end_date": "",
        "promote_start_time": 0, "promote_end_time": 0, "score_rank": 0, "review_total": 0, "left_time": 0,
        "is_show": 1, "catid": "67", "category": "Bikinis", "warecode": "ZQ01"
      }, {
        "goods_type": 0, "goods_id": "566060", "goods_sn": "280716603", "is_on_sale": "1", "goods_number": "37",
        "promte_percent": "0.94", "activity_number": "0", "activity_volume_number": "0",
        "goods_title": "ZAFUL Flower Twist High Waisted Bikini Set",
        "url_quick": "http://www.pc-zaful.com.v0731_tr.php5.egomsl.com/m-goods_fast-a-info.htm?goods_id=566060&ge_newindex=1",
        "url_title": "http://www.pc-zaful.com.v0731_tr.php5.egomsl.com/zaful-flower-twist-high-waisted-bikini-set-p_566060.html",
        "goods_img": "https://gloimg.zafcdn.com/zaful/pdm-product-pic/Clothing/2018/08/30/goods-img/1535990375812822275.jpg",
        "market_price": "15.99", "shop_price": "16.99", "discount": 0, "warehousecode": "ZQ01", "cateid": "67",
        "catename": "Bikinis", "promotions": [], "promote_start_date": "", "promote_end_date": "",
        "promote_start_time": 0, "promote_end_time": 0, "score_rank": 0, "review_total": 0, "left_time": 0,
        "is_show": 1, "catid": "67", "category": "Bikinis", "warecode": "ZQ01"
      }, {
        "goods_type": 0, "goods_id": "410581", "goods_sn": "232364203", "is_on_sale": "1", "goods_number": "82",
        "promte_percent": "1.13", "activity_number": "0", "activity_volume_number": "0",
        "goods_title": "Hooded Color Block Corduroy Jacket",
        "url_quick": "http://www.pc-zaful.com.v0731_tr.php5.egomsl.com/m-goods_fast-a-info.htm?goods_id=410581&ge_newindex=1",
        "url_title": "http://www.pc-zaful.com.v0731_tr.php5.egomsl.com/hooded-color-block-corduroy-jacket-p_410581.html",
        "goods_img": "https://gloimg.zafcdn.com/zaful/pdm-product-pic/Clothing/2017/12/08/goods-img/1512695836459019017.jpg",
        "market_price": "57.83", "shop_price": "50.99", "discount": 0, "warehousecode": "ZQ01", "cateid": "8",
        "catename": "Jackets & Coats", "promotions": [], "promote_start_date": "", "promote_end_date": "",
        "promote_start_time": 0, "promote_end_time": 0, "score_rank": 0, "review_total": 0, "left_time": 0,
        "is_show": 1, "catid": "8", "category": "Jackets & Coats", "warecode": "ZQ01"
      }, {
        "goods_type": 0, "goods_id": "554107", "goods_sn": "276459304", "is_on_sale": "1", "goods_number": "929",
        "promte_percent": "1.62", "activity_number": "0", "activity_volume_number": "0",
        "goods_title": "Chest Letter Print Solid Color Suede Sweatshirt",
        "url_quick": "http://www.pc-zaful.com.v0731_tr.php5.egomsl.com/m-goods_fast-a-info.htm?goods_id=554107&ge_newindex=1",
        "url_title": "http://www.pc-zaful.com.v0731_tr.php5.egomsl.com/chest-letter-print-solid-color-suede-sweatshirt-p_554107.html",
        "goods_img": "https://gloimg.zafcdn.com/zaful/pdm-product-pic/Clothing/2018/08/20/goods-img/1534723229607193480.jpg",
        "market_price": "45.25", "shop_price": "27.99", "discount": 0, "warehousecode": "ZQ01", "cateid": "139",
        "catename": "Hoodies & Sweatshirts", "promotions": [], "promote_start_date": "", "promote_end_date": "",
        "promote_start_time": 0, "promote_end_time": 0, "score_rank": 0, "review_total": 0, "left_time": 0,
        "is_show": 1, "catid": "139", "category": "Hoodies & Sweatshirts", "warecode": "ZQ01"
      }, {
        "goods_type": 0, "goods_id": "539257", "goods_sn": "268952802", "is_on_sale": "1", "goods_number": "0",
        "promte_percent": "0.84", "activity_number": "0", "activity_volume_number": "0",
        "goods_title": "Spaghetti Strap Criss Cross Bikini",
        "url_quick": "http://www.pc-zaful.com.v0731_tr.php5.egomsl.com/m-goods_fast-a-info.htm?goods_id=539257&ge_newindex=1",
        "url_title": "http://www.pc-zaful.com.v0731_tr.php5.egomsl.com/spaghetti-strap-criss-cross-bikini-p_539257.html",
        "goods_img": "https://gloimg.zafcdn.com/zaful/pdm-product-pic/Clothing/2018/06/07/goods-img/1533081148286074904.jpg",
        "market_price": "10.00", "shop_price": "11.97", "discount": -20, "warehousecode": "ZQ01", "cateid": "67",
        "catename": "Bikinis", "promotions": [], "promote_start_date": "2019-05-05", "promote_end_date": "2020-07-01",
        "promote_start_time": "1556985600", "promote_end_time": "1593532800", "score_rank": 0, "review_total": 0,
        "left_time": 29146184, "is_show": 1, "catid": "67", "category": "Bikinis", "warecode": "ZQ01"
      }, {
        "goods_type": 0, "goods_id": "566082", "goods_sn": "276426201", "is_on_sale": "1", "goods_number": "0",
        "promte_percent": "1.56", "activity_number": "0", "activity_volume_number": "0",
        "goods_title": "ZAFUL Two Tone Hoodie and Sports Pants Set",
        "url_quick": "http://www.pc-zaful.com.v0731_tr.php5.egomsl.com/m-goods_fast-a-info.htm?goods_id=566082&ge_newindex=1",
        "url_title": "http://www.pc-zaful.com.v0731_tr.php5.egomsl.com/zaful-two-tone-hoodie-and-sports-pants-set-p_566082.html",
        "goods_img": "https://gloimg.zafcdn.com/zaful/pdm-product-pic/Clothing/2018/08/30/goods-img/1535995023471077733.jpg",
        "market_price": "81.25", "shop_price": "51.99", "discount": 0, "warehousecode": "ZQ01", "cateid": "175",
        "catename": "Polo Shirts", "promotions": [], "promote_start_date": "", "promote_end_date": "",
        "promote_start_time": 0, "promote_end_time": 0, "score_rank": 0, "review_total": 0, "left_time": 0,
        "is_show": 1, "catid": "175", "category": "Polo Shirts", "warecode": "ZQ01"
      }
    ]
  }
}